QuickColab/Client.py
QuickColab/Console.py
QuickColab/Element.py
QuickColab/__init__.py
QuickColab/config.py
QuickColab/struc.py
QuickColab/prompts/__init__.py
QuickColab-1.0.0.dist-info/METADATA
QuickColab-1.0.0.dist-info/WHEEL
QuickColab-1.0.0.dist-info/entry_points.txt
QuickColab-1.0.0.dist-info/top_level.txt
QuickColab-1.0.0.dist-info/RECORD
