Metadata-Version: 2.1
Name: QuickColab
Version: 1.0.0
Summary: A package for Google Colab utility functions.
Home-page: https://github.com/yourusername/QuickColab
Author: TimmyLai
Author-email: lyyhkcc@gmail.com
Classifier: Programming Language :: Python :: 3
Classifier: License :: OSI Approved :: MIT License
Classifier: Operating System :: OS Independent
Requires-Python: >=3.6
Requires-Dist: ipywidgets
Requires-Dist: python-dotenv
Requires-Dist: openai
Requires-Dist: datasets
Requires-Dist: transformers
Requires-Dist: huggingsound
Requires-Dist: pillow
